CHANGES.txt
LICENSE.txt
MANIFEST.in
README.md
setup.py
pywizard_package_apt/__init__.py
pywizard_package_apt/package_provider.py
pywizard_package_apt.egg-info/PKG-INFO
pywizard_package_apt.egg-info/SOURCES.txt
pywizard_package_apt.egg-info/dependency_links.txt
pywizard_package_apt.egg-info/requires.txt
pywizard_package_apt.egg-info/top_level.txt