Metadata-Version: 1.0
Name: pywizard-package-apt
Version: 0.1.5
Summary: Apt package provider
Home-page: UNKNOWN
Author: Alex Rudakov
Author-email: ribozz@gmail.com
License: MIT
Platform: UNKNOWN
